mirantis/testing/metta/__init__.py
mirantis/testing/metta/bootstrap.py
mirantis/testing/metta/building.py
mirantis/testing/metta/client.py
mirantis/testing/metta/config.py
mirantis/testing/metta/discover.py
mirantis/testing/metta/environment.py
mirantis/testing/metta/fixture.py
mirantis/testing/metta/globals.py
mirantis/testing/metta/importing.py
mirantis/testing/metta/output.py
mirantis/testing/metta/plugin.py
mirantis/testing/metta/provisioner.py
mirantis/testing/metta/setuptools.py
mirantis/testing/metta/workload.py
mirantis/testing/metta_ansible/__init__.py
mirantis/testing/metta_ansible/ansiblecli.py
mirantis/testing/metta_ansible/ansiblecli_client.py
mirantis/testing/metta_ansible/ansiblecli_provisioner.py
mirantis/testing/metta_ansible/ansiblecli_workload.py
mirantis/testing/metta_ansible/ansibleinc_callback.py
mirantis/testing/metta_ansible/ansibleinc_play.py
mirantis/testing/metta_ansible/cli.py
mirantis/testing/metta_cli/__init__.py
mirantis/testing/metta_cli/base.py
mirantis/testing/metta_cli/config.py
mirantis/testing/metta_cli/entrypoint.py
mirantis/testing/metta_cli/environment.py
mirantis/testing/metta_cli/fixtures.py
mirantis/testing/metta_cli/output.py
mirantis/testing/metta_cli/provisioner.py
mirantis/testing/metta_cli/root.py
mirantis/testing/metta_common/__init__.py
mirantis/testing/metta_common/binhelper_utility.py
mirantis/testing/metta_common/combo_provisioner.py
mirantis/testing/metta_common/common_config.py
mirantis/testing/metta_common/config_format_output.py
mirantis/testing/metta_common/dict_output.py
mirantis/testing/metta_common/text_output.py
mirantis/testing/metta_common/user_cli.py
mirantis/testing/metta_docker/__init__.py
mirantis/testing/metta_docker/cli.py
mirantis/testing/metta_docker/client.py
mirantis/testing/metta_docker/run_workload.py
mirantis/testing/metta_dummy/__init__.py
mirantis/testing/metta_dummy/client.py
mirantis/testing/metta_dummy/provisioner.py
mirantis/testing/metta_dummy/workload.py
mirantis_metta-0.50.1.dist-info/LICENSE
mirantis_metta-0.50.1.dist-info/METADATA
mirantis_metta-0.50.1.dist-info/WHEEL
mirantis_metta-0.50.1.dist-info/entry_points.txt
mirantis_metta-0.50.1.dist-info/top_level.txt
mirantis_metta-0.50.1.dist-info/RECORD
