Metadata-Version: 2.1
Name: mirantis-metta
Version: 0.50.1
Summary: Python Toolbox for testing mirantis products
Home-page: https://mirantis.com/
Author: James Nesbitt
Author-email: jnesbitt@mirantis.com
License: MIT
Project-URL: Source, https://github.com/james-nesbitt/metta
Keywords: test,unittest
Platform: unix
Platform: linux
Platform: osx
Classifier: Development Status :: 4 - Beta
Classifier: Intended Audience :: Developers
Classifier: License :: OSI Approved :: MIT License
Classifier: Operating System :: MacOS :: MacOS X
Classifier: Operating System :: POSIX
Classifier: Programming Language :: Python :: 3
Classifier: Programming Language :: Python :: 3 :: Only
Classifier: Programming Language :: Python :: 3.9
Classifier: Topic :: Software Development :: Libraries
Classifier: Topic :: Software Development :: Testing
Classifier: Topic :: Utilities
License-File: LICENSE
Requires-Dist: appdirs
Requires-Dist: configerus (>=3.0.1)
Requires-Dist: pyyaml
Requires-Dist: docker[tls] (~=5.0.0)
Requires-Dist: kubernetes (==18.20.0)
Requires-Dist: fire
Requires-Dist: requests
Requires-Dist: toml
Requires-Dist: py3winrm
Requires-Dist: paramiko
